crackme_template/__init__.py
crackme_template/main.py
crackme_template/version.py
crackme_template-0.0.2.dist-info/LICENSE
crackme_template-0.0.2.dist-info/METADATA
crackme_template-0.0.2.dist-info/WHEEL
crackme_template-0.0.2.dist-info/entry_points.txt
crackme_template-0.0.2.dist-info/top_level.txt
crackme_template-0.0.2.dist-info/RECORD
