Metadata-Version: 2.1
Name: crackme-template
Version: 0.0.2
Summary: Crackme Template
Home-page: https://github.com/nymann/crackme-template
Maintainer: Kristian Nymann Jakobsen
Maintainer-email: kristian@nymann.dev
License: UNKNOWN
Platform: UNKNOWN
Requires-Python: >=3.9
License-File: LICENSE
Requires-Dist: typer (>=0.4.1)
Requires-Dist: cookiecutter (>=1.7.3)
Requires-Dist: PyGithub (>=1.55)
Requires-Dist: crackmes-dl (>=1.0.4)
Provides-Extra: all
Requires-Dist: isort ; extra == 'all'
Requires-Dist: wemake-python-styleguide ; extra == 'all'
Requires-Dist: mypy ; extra == 'all'
Requires-Dist: black ; extra == 'all'
Requires-Dist: nitpick ; extra == 'all'
Requires-Dist: add-trailing-comma ; extra == 'all'
Requires-Dist: pytest ; extra == 'all'
Requires-Dist: pytest-cov ; extra == 'all'
Requires-Dist: pytest-mock ; extra == 'all'
Provides-Extra: dev
Requires-Dist: isort ; extra == 'dev'
Requires-Dist: wemake-python-styleguide ; extra == 'dev'
Requires-Dist: mypy ; extra == 'dev'
Requires-Dist: black ; extra == 'dev'
Requires-Dist: nitpick ; extra == 'dev'
Requires-Dist: add-trailing-comma ; extra == 'dev'
Provides-Extra: tests
Requires-Dist: pytest ; extra == 'tests'
Requires-Dist: pytest-cov ; extra == 'tests'
Requires-Dist: pytest-mock ; extra == 'tests'
